jl_remote_connection_helper/__init__.py
jl_remote_connection_helper/_version.py
jl_remote_connection_helper/handlers.py
jl_remote_connection_helper-0.1.1.data/data/etc/jupyter/jupyter_server_config.d/jl_remote_connection_helper.json
jl_remote_connection_helper-0.1.1.data/data/share/jupyter/labextensions/jl-remote-connection-helper/package.json
jl_remote_connection_helper-0.1.1.data/data/share/jupyter/labextensions/jl-remote-connection-helper/schemas/jl-remote-connection-helper/package.json.orig
jl_remote_connection_helper-0.1.1.data/data/share/jupyter/labextensions/jl-remote-connection-helper/schemas/jl-remote-connection-helper/plugin.json
jl_remote_connection_helper-0.1.1.data/data/share/jupyter/labextensions/jl-remote-connection-helper/static/347.96d949608f89011254e2.js
jl_remote_connection_helper-0.1.1.data/data/share/jupyter/labextensions/jl-remote-connection-helper/static/347.96d949608f89011254e2.js.LICENSE.txt
jl_remote_connection_helper-0.1.1.data/data/share/jupyter/labextensions/jl-remote-connection-helper/static/58.97a9b60fe48efbe3178d.js
jl_remote_connection_helper-0.1.1.data/data/share/jupyter/labextensions/jl-remote-connection-helper/static/747.f354e353cb136c286ba5.js
jl_remote_connection_helper-0.1.1.data/data/share/jupyter/labextensions/jl-remote-connection-helper/static/remoteEntry.30a82e887a9ee5f6ece6.js
jl_remote_connection_helper-0.1.1.data/data/share/jupyter/labextensions/jl-remote-connection-helper/static/style.js
jl_remote_connection_helper-0.1.1.data/data/share/jupyter/labextensions/jl-remote-connection-helper/static/third-party-licenses.json
jl_remote_connection_helper-0.1.1.data/data/share/jupyter/labextensions/jl-remote-connection-helper/install.json
jl_remote_connection_helper-0.1.1.dist-info/METADATA
jl_remote_connection_helper-0.1.1.dist-info/WHEEL
jl_remote_connection_helper-0.1.1.dist-info/licenses/LICENSE
jl_remote_connection_helper-0.1.1.dist-info/RECORD
